job_stalker/__init__.py
job_stalker/ai_client.py
job_stalker/cache.py
job_stalker/config.py
job_stalker/database.py
job_stalker/db.py
job_stalker/exceptions.py
job_stalker/filters.py
job_stalker/gpu_monitor.py
job_stalker/main.py
job_stalker/ml_filter.py
job_stalker/models.py
job_stalker/paths.py
job_stalker/run.py
job_stalker/state.py
job_stalker/telegram_auth.py
job_stalker/vacancy_storage.py
job_stalker/web_ui.py
job_stalker/static-files/auth.css
job_stalker/static-files/auth.js
job_stalker/static-files/background/back.jpg
job_stalker/static-files/background/back1.jpg
job_stalker/static-files/css/style.css
job_stalker/static-files/icons/play.png
job_stalker/static-files/images/1.png
job_stalker/static-files/images/2.png
job_stalker/static-files/images/3.png
job_stalker/static-files/images/4.png
job_stalker/static-files/images/5.png
job_stalker/static-files/images/Banner.png
job_stalker/templates-html/index.html
job_stalker/vacancy_parser/__init__.py
job_stalker/vacancy_parser/anchors.py
job_stalker/vacancy_parser/content.py
job_stalker/vacancy_parser/models.py
job_stalker/vacancy_parser/normalizer.py
job_stalker/vacancy_parser/parser.py
job_stalker/vacancy_parser/rules.py
job_stalker/vacancy_parser/semantics.py
job_stalker-0.3.0.dist-info/METADATA
job_stalker-0.3.0.dist-info/WHEEL
job_stalker-0.3.0.dist-info/entry_points.txt
job_stalker-0.3.0.dist-info/top_level.txt
job_stalker-0.3.0.dist-info/RECORD
