Metadata-Version: 2.4
Name: job-stalker
Version: 0.3.0
Summary: Telegram bot that filters job vacancies with a web UI
Author-email: 10sorry <rip.pip.pip@yandex.ru>
License-Expression: MIT
Project-URL: Homepage, https://github.com/10sorry/JobStalker
Requires-Python: >=3.11
Requires-Dist: fastapi
Requires-Dist: uvicorn[standard]
Requires-Dist: pyrogram
Requires-Dist: aiosqlite
Requires-Dist: python-dotenv
Requires-Dist: aiohttp
Requires-Dist: rich
Requires-Dist: psutil
Requires-Dist: jinja2
Requires-Dist: pydantic
Requires-Dist: pypdf
Requires-Dist: python-docx
Requires-Dist: beautifulsoup4
Provides-Extra: gpu
Requires-Dist: pynvml; (platform_system == "Linux" or platform_system == "Windows") and extra == "gpu"
Requires-Dist: pyamdgpuinfo; platform_system == "Linux" and extra == "gpu"
